ssttkkl_nonebot_utils/__init__.py
ssttkkl_nonebot_utils/config_loader.py
ssttkkl_nonebot_utils/errors/__init__.py
ssttkkl_nonebot_utils/errors/error_handler.py
ssttkkl_nonebot_utils/errors/errors.py
ssttkkl_nonebot_utils/integer.py
ssttkkl_nonebot_utils/interceptor/__init__.py
ssttkkl_nonebot_utils/interceptor/handle_error.py
ssttkkl_nonebot_utils/interceptor/with_graceful_shutdown.py
ssttkkl_nonebot_utils/interceptor/with_handling_reaction.py
ssttkkl_nonebot_utils/nonebot.py
ssttkkl_nonebot_utils/platform/__init__.py
ssttkkl_nonebot_utils/platform/extract_mention_user/__init__.py
ssttkkl_nonebot_utils/platform/extract_mention_user/onebot/__init__.py
ssttkkl_nonebot_utils/platform/extract_mention_user/onebot/v11.py
ssttkkl_nonebot_utils/platform/extract_mention_user/qqguild.py
ssttkkl_nonebot_utils/platform/func_manager.py
ssttkkl_nonebot_utils/platform/get_user_nickname/__init__.py
ssttkkl_nonebot_utils/platform/get_user_nickname/cache.py
ssttkkl_nonebot_utils/platform/get_user_nickname/fallback.py
ssttkkl_nonebot_utils/platform/get_user_nickname/kaiheila.py
ssttkkl_nonebot_utils/platform/get_user_nickname/onebot/__init__.py
ssttkkl_nonebot_utils/platform/get_user_nickname/onebot/v11.py
ssttkkl_nonebot_utils/platform/get_user_nickname/qqguild.py
ssttkkl_nonebot_utils/platform/handling_reaction/__init__.py
ssttkkl_nonebot_utils/platform/handling_reaction/fallback.py
ssttkkl_nonebot_utils/platform/handling_reaction/kaiheila.py
ssttkkl_nonebot_utils/platform/handling_reaction/qqguild.py
ssttkkl_nonebot_utils/platform/is_destination_available/__init__.py
ssttkkl_nonebot_utils/platform/is_destination_available/kaiheila.py
ssttkkl_nonebot_utils/platform/is_destination_available/onebot/__init__.py
ssttkkl_nonebot_utils/platform/is_destination_available/onebot/v11.py
ssttkkl_nonebot_utils/platform/is_group_admin/__init__.py
ssttkkl_nonebot_utils/platform/is_group_admin/onebot/__init__.py
ssttkkl_nonebot_utils/platform/is_group_admin/onebot/v11.py
ssttkkl_nonebot_utils-0.1.23.dist-info/METADATA
ssttkkl_nonebot_utils-0.1.23.dist-info/WHEEL
ssttkkl_nonebot_utils-0.1.23.dist-info/RECORD
