Metadata-Version: 2.3
Name: ssttkkl-nonebot-utils
Version: 0.1.23
Summary: ssttkkl-nonebot-utils
License: MIT
Author: ssttkkl
Author-email: huang.wen.long@hotmail.com
Requires-Python: >=3.8,<4.0
Classifier: License :: OSI Approved :: MIT License
Classifier: Programming Language :: Python :: 3
Classifier: Programming Language :: Python :: 3.8
Classifier: Programming Language :: Python :: 3.9
Classifier: Programming Language :: Python :: 3.10
Classifier: Programming Language :: Python :: 3.11
Classifier: Programming Language :: Python :: 3.12
Classifier: Programming Language :: Python :: 3.13
Requires-Dist: aiofiles (>=23.2.1)
Requires-Dist: asyncache (>=0.3.1)
Requires-Dist: cachetools (>=5.3.1)
Requires-Dist: nonebot-plugin-localstore (>=0.3.0)
Requires-Dist: nonebot-plugin-send-anything-anywhere (>=0.3.0)
Requires-Dist: nonebot-plugin-session (>=0.1.0)
Requires-Dist: nonebot2 (>=2.0.0,<3.0.0)
